vidavis/LICENSE.rst
vidavis/__init__.py
vidavis/apps/__init__.py
vidavis/apps/_ms_raster.py
vidavis/bokeh/__init__.py
vidavis/bokeh/_palette.py
vidavis/data/__init__.py
vidavis/data/measurement_set/__init__.py
vidavis/data/measurement_set/_ms_data.py
vidavis/data/measurement_set/processing_set/__init__.py
vidavis/data/measurement_set/processing_set/_ps_concat.py
vidavis/data/measurement_set/processing_set/_ps_coords.py
vidavis/data/measurement_set/processing_set/_ps_data.py
vidavis/data/measurement_set/processing_set/_ps_io.py
vidavis/data/measurement_set/processing_set/_ps_raster_data.py
vidavis/data/measurement_set/processing_set/_ps_select.py
vidavis/data/measurement_set/processing_set/_ps_stats.py
vidavis/data/measurement_set/processing_set/_xds_data.py
vidavis/plot/__init__.py
vidavis/plot/ms_plot/__init__.py
vidavis/plot/ms_plot/_check_raster_inputs.py
vidavis/plot/ms_plot/_locate_points.py
vidavis/plot/ms_plot/_ms_plot.py
vidavis/plot/ms_plot/_ms_plot_constants.py
vidavis/plot/ms_plot/_ms_plot_selectors.py
vidavis/plot/ms_plot/_plot_inputs.py
vidavis/plot/ms_plot/_raster_plot.py
vidavis/plot/ms_plot/_raster_plot_gui.py
vidavis/plot/ms_plot/_raster_plot_inputs.py
vidavis/plot/ms_plot/_time_ticks.py
vidavis/plot/ms_plot/_xds_plot_axes.py
vidavis/toolbox/__init__.py
vidavis/toolbox/_app_context.py
vidavis/toolbox/_logging.py
vidavis/toolbox/_static.py
vidavis/__version__.py
vidavis-0.1.3.dist-info/WHEEL
vidavis-0.1.3.dist-info/METADATA
vidavis-0.1.3.dist-info/licenses/LICENSE
vidavis-0.1.3.dist-info/RECORD
