Metadata-Version: 2.1
Name: vidavis
Version: 0.1.3
Summary: Radio astronomy visibility data visualization
License: LGPL
Author-email: Darrell Schiebel <darrell@schiebel.us>,Pam Harris <pharris@nrao.edu>
Requires-Python: >=3.11, <3.14
Requires-Dist: bokeh<3.9,>=3.7
Requires-Dist: graphviper
Requires-Dist: hvplot
Requires-Dist: matplotlib
Requires-Dist: panel==1.8.2
Requires-Dist: selenium
